concatenate/__init__.py
concatenate-0.1.2.dist-info/LICENSE
concatenate-0.1.2.dist-info/WHEEL
concatenate-0.1.2.dist-info/METADATA
concatenate-0.1.2.dist-info/RECORD
