Metadata-Version: 2.1
Name: concatenate
Version: 0.1.2
Summary: Concatenate two objects of the same type
Home-page: https://github.com/tombulled/concatenate
License: MIT
Keywords: python,concatenate,join
Author: Tom Bulled
Author-email: 26026015+tombulled@users.noreply.github.com
Requires-Python: >=3.8,<4.0
Classifier: License :: OSI Approved :: MIT License
Classifier: Programming Language :: Python :: 3
Classifier: Programming Language :: Python :: 3.10
Classifier: Programming Language :: Python :: 3.8
Classifier: Programming Language :: Python :: 3.9
Requires-Dist: registrate (>=0.1.6,<0.2.0)
Project-URL: Repository, https://github.com/tombulled/concatenate
